translations/__init__.py
translations/admin.py
translations/apps.py
translations/context.py
translations/forms.py
translations/languages.py
translations/models.py
translations/query.py
translations/querysets.py
translations/utils.py
translations/management/__init__.py
translations/management/commands/__init__.py
translations/management/commands/synctranslations.py
translations/migrations/0001_initial.py
translations/migrations/0002_auto_20180920_1245.py
translations/migrations/__init__.py
django_translations_version_4-1.0.dist-info/LICENSE
django_translations_version_4-1.0.dist-info/METADATA
django_translations_version_4-1.0.dist-info/WHEEL
django_translations_version_4-1.0.dist-info/top_level.txt
django_translations_version_4-1.0.dist-info/RECORD
